arg_econ_data/BancoMundial.py
arg_econ_data/BymaData.py
arg_econ_data/ENGHo.py
arg_econ_data/EPH.py
arg_econ_data/PresupuestoAbierto.py
arg_econ_data/Series.py
arg_econ_data/YahooFinance.py
arg_econ_data/__init__.py
arg_econ_data-0.0.21.dist-info/METADATA
arg_econ_data-0.0.21.dist-info/WHEEL
arg_econ_data-0.0.21.dist-info/top_level.txt
arg_econ_data-0.0.21.dist-info/RECORD
