Metadata-Version: 2.1
Name: arg-econ-data
Version: 0.0.21
Requires-Dist: pandas (>=1.3.5)
Requires-Dist: requests (>=2.26.0)
Requires-Dist: wget (<4.0,>=3.2)
Requires-Dist: wbgapi (>=1.0.7)
Requires-Dist: yfinance (>=0.1.70)
Requires-Dist: pandas-datareader (>=0.10.0)
